{"cameraMode":{"drawMode":0,"name":"Shaded","section":"Shading Mode"},"sceneLighting":true,"audioPlay":false,"sceneViewState":{"m_AlwaysRefresh":false,"showFog":true,"showSkybox":true,"showFlares":true,"showImageEffects":true,"showParticleSystems":true,"showVisualEffectGraphs":true,"m_FxEnabled":true},"in2DMode":false,"pivot":{"x":2622.236572265625,"y":586.10009765625,"z":798.5482788085938},"rotation":{"x":-0.04725685343146324,"y":0.6597405076026917,"z":-0.05123551934957504,"w":-0.7496389746665955},"size":164.50839233398438,"orthographic":false}